manager/__init__.py
manager/__main__.py
manager/cli.py
manager/data_manager/__init__.py
manager/data_manager/portmirror_config.py
manager/data_manager/vlan_config.py
botblox-1.0.10.dist-info/LICENSE
botblox-1.0.10.dist-info/METADATA
botblox-1.0.10.dist-info/WHEEL
botblox-1.0.10.dist-info/entry_points.txt
botblox-1.0.10.dist-info/top_level.txt
botblox-1.0.10.dist-info/RECORD
