Metadata-Version: 2.1
Name: botblox
Version: 1.0.10
Summary: BotBlox Manager CLI tool
Home-page: https://github.com/botblox/botblox-manager-software
Author: Aaron Elijah
Author-email: aaronzakelijah@googlemail.com
License: MIT
Platform: UNKNOWN
Classifier: License :: OSI Approved :: MIT License
Classifier: Programming Language :: Python :: 3.6
Classifier: Programming Language :: Python :: 3.7
Classifier: Programming Language :: Python :: 3.8
Classifier: Operating System :: OS Independent
Requires-Python: >=3.6
Requires-Dist: pyserial (>=3.5)
Provides-Extra: dev
Requires-Dist: flake8 (==3.8.4) ; extra == 'dev'
Requires-Dist: flake8-import-order (==0.18.1) ; extra == 'dev'
Requires-Dist: flake8-builtins (==1.5.3) ; extra == 'dev'
Requires-Dist: flake8-docstrings (==1.5.0) ; extra == 'dev'
Requires-Dist: flake8-rst-docstrings (==0.0.14) ; extra == 'dev'
Requires-Dist: flake8-annotations (==2.4.1) ; extra == 'dev'
Requires-Dist: flake8-print (==4.0.0) ; extra == 'dev'
Requires-Dist: pep8-naming (==0.11.1) ; extra == 'dev'
